sphinxpapyrus_docxbuilder-0.1.1-py2.7-nspkg.pth
sphinxpapyrus/docxbuilder/__init__.py
sphinxpapyrus/docxbuilder/builder.py
sphinxpapyrus/docxbuilder/writer.py
sphinxpapyrus/docxbuilder/templates/style.docx
sphinxpapyrus_docxbuilder-0.1.1.dist-info/METADATA
sphinxpapyrus_docxbuilder-0.1.1.dist-info/RECORD
sphinxpapyrus_docxbuilder-0.1.1.dist-info/WHEEL
sphinxpapyrus_docxbuilder-0.1.1.dist-info/namespace_packages.txt
sphinxpapyrus_docxbuilder-0.1.1.dist-info/top_level.txt
