Metadata-Version: 2.1
Name: sphinxpapyrus-docxbuilder
Version: 0.1.1
Summary: A Sphinx extension for Word (.docx) file output
Home-page: https://github.com/nakandev/sphinxpapyrus-docxbuilder
Author: nakandev
Author-email: nakandev.s@gmail.com
License: MIT
Platform: any
Requires-Dist: python-docx
